{
    "title": "Barack Obama attacks Trump administration's response to coronavirus pandemic",
    "text": [
        {
            "id": 0,
            "text": "Barack Obama has attacked the Trump administration\u2019s response to the Covid-19 pandemic during speeches to graduating students."
        },
        {
            "id": 1,
            "text": "The comments on Saturday were a rare rebuke of a sitting president from one of his predecessors, and come in the midst of the coronavirus pandemic that has killed more than 88,000 people in the United States, a death toll far higher than any other country, and had devastating and disproportionate effects on communities of color."
        },
        {
            "id": 2,
            "text": "\u201cMore than anything, this pandemic has fully, finally torn back the curtain on the idea that so many of the folks in charge know what they\u2019re doing."
        },
        {
            "id": 3,
            "text": "A lot of them aren\u2019t even pretending to be in charge,\u201d Obama said during an online commencement address to graduates of historically black colleges and universities (HBCUs) on Saturday."
        },
        {
            "id": 4,
            "text": "\u201cDoing what feels good, what\u2019s convenient, what\u2019s easy \u2014 that\u2019s how little kids think,\u201d he said in a second virtual speech on Saturday evening for graduating US high school students."
        },
        {
            "id": 5,
            "text": "\u201cUnfortunately, a lot of so-called grown-ups, including some with fancy titles and important jobs, still think that way \u2014 which is why things are so screwed up."
        },
        {
            "id": 6,
            "text": "\u201cI hope that instead, you decide to ground yourself in values that last, like honesty, hard work, responsibility, fairness, generosity, respect for others.\u201d"
        },
        {
            "id": 7,
            "text": "In an interview with ABC news, Peter Navarro, a top economic adviser to the president, said he was \u201cglad Mr Obama has a new job as Joe Biden\u2019s press secretary\u201d."
        },
        {
            "id": 8,
            "text": "Biden, Obama\u2019s former vice president, is running against Trump for president."
        },
        {
            "id": 9,
            "text": "The former president\u2019s comments came amid dual crises \u2013 one a pandemic disproportionately sickening people of color in the US, and another born by the economic impacts of attempts to contain the virus through lockdowns."
        },
        {
            "id": 10,
            "text": "So far, there have been 1.4 million confirmed cases of Covid-19 in the US."
        },
        {
            "id": 11,
            "text": "\u201cLet\u2019s be honest, a disease like this just spotlights the underlying inequalities and extra burdens that black communities have historically had to deal with in this country,\u201d said Obama in the HBCU speech."
        },
        {
            "id": 12,
            "text": "\u201cWe see it in the disproportionate impact of Covid-19 on our communities.\u201d"
        },
        {
            "id": 13,
            "text": "Those crises, as well as the high-profile killings of black people by police, loomed large in the virtual event, itself necessitated by the shutdown of large gatherings to stem the spread of the disease."
        },
        {
            "id": 14,
            "text": "\u201cThese aren\u2019t normal times."
        },
        {
            "id": 15,
            "text": "You\u2019re being asked to find your way in a world in the middle of a devastating pandemic and a terrible recession,\u201d said Obama."
        },
        {
            "id": 16,
            "text": "He added that the injustices faced by African Americans are not new, and described the recent high-profile killing of Ahmaud Arbery, an unarmed black jogger who was shot and killed after being pursued in broad daylight by a white former police officer and his son through a neighborhood in Georgia."
        },
        {
            "id": 17,
            "text": "\u201cWe see it when a black man goes for a jog and some folks feel like they can stop and question and shoot him, if he doesn\u2019t submit to their questioning,\u201d said Obama."
        },
        {
            "id": 18,
            "text": "Congrats to the high school Class of 2020, as well as to the teachers, coaches, and most of all, parents and family who\u2019ve guided you along the way."
        },
        {
            "id": 19,
            "text": "Thanks for letting me be part of your big day!"
        },
        {
            "id": 20,
            "text": ""
        },
        {
            "id": 21,
            "text": "May 17, 2020"
        },
        {
            "id": 22,
            "text": "He went on to use the circumstances of the online graduation as a rallying cry for new graduates: \u201cIf the world\u2019s going to get better, it\u2019s going to be up to you.\u201d"
        },
        {
            "id": 23,
            "text": "Although Obama has largely avoided criticizing Trump\u2019s performance in office, in a call leaked last week the former president described the US government\u2019s coronavirus response as, \u201can absolute chaotic disaster,\u201d and questioned whether the justice department\u2019s decision to drop charges against former national security advisor Michael Flynn could endanger the \u201crule of law\u201d in the United States."
        },
        {
            "id": 24,
            "text": "The remarks prompted the US Senate majority leader, Mitch McConnell, to tell the former president to \u201ckeep his mouth shut\u201d."
        },
        {
            "id": 25,
            "text": "The week also saw the emergence of #Obamagate, a conspiracy theory pushed by the president that accuses Obama of attempting to frame Trump for colluding with Russia to win the 2016 election."
        },
        {
            "id": 26,
            "text": "One former CIA analyst described as \u201ca hashtag in search of a scandal\u201d."
        },
        {
            "id": 27,
            "text": "Obama\u2019s remarks were preceded by speeches and performances by musicians, actors and entertainers such as Steve Harvey, Anthony Hamilton, Doug E Fresh, Wyclef Jean, Common, Kevin Hart, Wendy Raquel Robinson and Vivica A Fox."
        },
        {
            "id": 28,
            "text": "Messages to graduates tuning in online because they could not hold traditional celebrations on campus were shot through with acknowledgements of America\u2019s history of racial segregation."
        },
        {
            "id": 29,
            "text": "This, speakers said, made the universities essential, while noting the perseverance required to spend a final semester largely online, and the bittersweetness of the moment itself."
        },
        {
            "id": 30,
            "text": "\u201cThis is obviously not the way you wanted to graduate, we get that,\u201d said Doc Rivers, coach of the NBA\u2019s Los Angeles Clippers, \u201cBut you know what else we know?"
        },
        {
            "id": 31,
            "text": "You\u2019re going to make us all proud.\u201d"
        },
        {
            "id": 32,
            "text": "Graduates, speakers said, would be sent out into an \u201cuncertain world,\u201d but one they had a chance to improve upon."
        },
        {
            "id": 33,
            "text": "\u201cAs graduates, you now join the ranks of national and world leaders, influencers,\u201d said Senator Kamala Harris of California."
        },
        {
            "id": 34,
            "text": "\u201cI know this is a trying time, but please do not let the moment of this crisis dampen your ambitions, your hopes or your dreams, because your country needs you,\u201d said Harris."
        },
        {
            "id": 35,
            "text": "She attended the HBCU Howard, recently ran for the Democratic nomination and is a contender to become Joe Biden\u2019s running mate in the 2020 election."
        }
    ]
}