{
    "title": "Representative Andy Biggs: Maxine Waters Should Resign",
    "entity lists": [
        [
            "Andy Biggs",
            [
                "People"
            ],
            [
                "Salient"
            ],
            [
                "B"
            ]
        ],
        [
            "Maxine Waters",
            [
                "People"
            ],
            [
                "Main"
            ],
            [
                "B"
            ]
        ],
        [
            "Donald Trump",
            [
                "People"
            ],
            [
                "Salient"
            ],
            [
                "B"
            ]
        ]
    ],
    "sentence-level stances": {
        "0": [
            {
                "id": 0,
                "subject": "Andy Biggs",
                "sentiment": "NEG",
                "object": "Maxine Waters",
                "annotators": [
                    "B"
                ]
            }
        ],
        "1": [
            {
                "id": 0,
                "subject": "Andy Biggs",
                "sentiment": "NEG",
                "object": "Maxine Waters",
                "annotators": [
                    "B"
                ]
            }
        ],
        "2": [
            {
                "id": 0,
                "subject": "Maxine Waters",
                "sentiment": "NEG",
                "object": "Donald Trump",
                "annotators": [
                    "B"
                ]
            }
        ],
        "3": [
            {
                "id": 0,
                "subject": "Maxine Waters",
                "sentiment": "NEG",
                "object": "Donald Trump",
                "annotators": [
                    "B"
                ]
            }
        ],
        "4": [
            {
                "id": 0,
                "subject": "Andy Biggs",
                "sentiment": "NEG",
                "object": "Maxine Waters",
                "annotators": [
                    "B"
                ]
            }
        ],
        "5": [
            {
                "id": 0,
                "subject": "Not in the list",
                "sentiment": "NEG",
                "object": "Maxine Waters",
                "annotators": [
                    "B"
                ]
            },
            {
                "id": 1,
                "subject": "Andy Biggs",
                "sentiment": "NEG",
                "object": "Maxine Waters",
                "annotators": [
                    "B"
                ]
            }
        ],
        "6": [
            {
                "id": 0,
                "subject": "Not in the list",
                "sentiment": "NEG",
                "object": "Maxine Waters",
                "annotators": [
                    "B"
                ]
            },
            {
                "id": 1,
                "subject": "Andy Biggs",
                "sentiment": "NEG",
                "object": "Maxine Waters",
                "annotators": [
                    "B"
                ]
            }
        ],
        "7": [
            {
                "id": 0,
                "subject": "Not in the list",
                "sentiment": "NEG",
                "object": "Maxine Waters",
                "annotators": [
                    "B"
                ]
            },
            {
                "id": 1,
                "subject": "Andy Biggs",
                "sentiment": "NEG",
                "object": "Maxine Waters",
                "annotators": [
                    "B"
                ]
            }
        ],
        "8": [
            {
                "id": 0,
                "subject": "Not in the list",
                "sentiment": "NEG",
                "object": "Maxine Waters",
                "annotators": [
                    "B"
                ]
            },
            {
                "id": 1,
                "subject": "Andy Biggs",
                "sentiment": "NEG",
                "object": "Maxine Waters",
                "annotators": [
                    "B"
                ]
            }
        ]
    },
    "entity sentiments": {
        "Maxine Waters": [
            [
                "Very Negative",
                "B"
            ]
        ],
        "Donald Trump": [
            [
                "Neutral",
                "B"
            ]
        ],
        "Andy Biggs": [
            [
                "Neutral",
                "B"
            ]
        ]
    },
    "entity ideologies": {
        "Maxine Waters": [
            [
                "Very Liberal",
                "B"
            ]
        ],
        "Donald Trump": [
            [
                "Very Conservative",
                "B"
            ]
        ],
        "Andy Biggs": [
            [
                "Conservative",
                "B"
            ]
        ]
    },
    "article ideology": [
        {
            "ideology": "Conservative",
            "annotator": "B"
        }
    ]
}